setup.py
hepdata_rootcnv.egg-info/PKG-INFO
hepdata_rootcnv.egg-info/SOURCES.txt
hepdata_rootcnv.egg-info/dependency_links.txt
hepdata_rootcnv.egg-info/entry_points.txt
hepdata_rootcnv.egg-info/requires.txt
hepdata_rootcnv.egg-info/top_level.txt
hepdatarootcnv/__init__.py
hepdatarootcnv/cli.py
hepdatarootcnv/formatters.py