Metadata-Version: 1.0
Name: hepdata-rootcnv
Version: 0.0.1
Summary: flexible conversion form ROOT to HepData YAML
Home-page: UNKNOWN
Author: Lukas Heinrich
Author-email: lukas.heinrich@cern.ch
License: UNKNOWN
Platform: UNKNOWN
